{
"meta":{"test_sets":["test"],"test_metrics":[{"best_value":"Min","name":"MAE"}],"learn_metrics":[{"best_value":"Min","name":"MAE"}],"launch_mode":"Train","parameters":"parameters","iteration_count":96,"learn_sets":["learn"],"name":"experiment"},
"iterations":[
{"parameters":[{"depth":2,"learning_rate":0.03,"l2_leaf_reg":0.2,"iterations":100}],"learn":[234.1195885],"iteration":0,"passed_time":1.742435641,"remaining_time":165.5313859,"test":[225.7405161]},
{"parameters":[{"depth":2,"learning_rate":0.1,"l2_leaf_reg":0.2,"iterations":100}],"learn":[218.8157623],"iteration":1,"passed_time":2.992668849,"remaining_time":140.6554359,"test":[211.8320444]},
{"parameters":[{"depth":2,"learning_rate":0.03,"l2_leaf_reg":0.5,"iterations":100}],"learn":[234.1195885],"iteration":2,"passed_time":4.239989723,"remaining_time":131.4396814,"test":[225.7405161]},
{"parameters":[{"depth":2,"learning_rate":0.1,"l2_leaf_reg":0.5,"iterations":100}],"learn":[218.8157623],"iteration":3,"passed_time":5.587466345,"remaining_time":128.5117259,"test":[211.8320444]},
{"parameters":[{"depth":2,"learning_rate":0.03,"l2_leaf_reg":1,"iterations":100}],"learn":[234.1195885],"iteration":4,"passed_time":6.809855667,"remaining_time":123.9393731,"test":[225.7405161]},
{"parameters":[{"depth":2,"learning_rate":0.1,"l2_leaf_reg":1,"iterations":100}],"learn":[218.8157623],"iteration":5,"passed_time":8.069572534,"remaining_time":121.043588,"test":[211.8320444]},
{"parameters":[{"depth":2,"learning_rate":0.03,"l2_leaf_reg":3,"iterations":100}],"learn":[234.1195885],"iteration":6,"passed_time":9.353386511,"remaining_time":118.9216285,"test":[225.7405161]},
{"parameters":[{"depth":2,"learning_rate":0.1,"l2_leaf_reg":3,"iterations":100}],"learn":[218.8157623],"iteration":7,"passed_time":10.4811087,"remaining_time":115.2921957,"test":[211.8320444]},
{"parameters":[{"depth":2,"learning_rate":0.03,"l2_leaf_reg":0.2,"iterations":150}],"learn":[222.6104906],"iteration":8,"passed_time":12.29050724,"remaining_time":118.8082367,"test":[215.0551813]},
{"parameters":[{"depth":2,"learning_rate":0.1,"l2_leaf_reg":0.2,"iterations":150}],"learn":[218.7515254],"iteration":9,"passed_time":14.06344033,"remaining_time":120.9455868,"test":[211.6668957]},
{"parameters":[{"depth":2,"learning_rate":0.03,"l2_leaf_reg":0.5,"iterations":150}],"learn":[222.6104906],"iteration":10,"passed_time":16.32151863,"remaining_time":126.1208258,"test":[215.0551813]},
{"parameters":[{"depth":2,"learning_rate":0.1,"l2_leaf_reg":0.5,"iterations":150}],"learn":[218.7515254],"iteration":11,"passed_time":18.49147879,"remaining_time":129.4403515,"test":[211.6668957]},
{"parameters":[{"depth":2,"learning_rate":0.03,"l2_leaf_reg":1,"iterations":150}],"learn":[222.6104906],"iteration":12,"passed_time":20.67900905,"remaining_time":132.0275193,"test":[215.0551813]},
{"parameters":[{"depth":2,"learning_rate":0.1,"l2_leaf_reg":1,"iterations":150}],"learn":[218.7515254],"iteration":13,"passed_time":23.15695634,"remaining_time":135.6336014,"test":[211.6668957]},
{"parameters":[{"depth":2,"learning_rate":0.03,"l2_leaf_reg":3,"iterations":150}],"learn":[222.6104906],"iteration":14,"passed_time":25.88493087,"remaining_time":139.7786267,"test":[215.0551813]},
{"parameters":[{"depth":2,"learning_rate":0.1,"l2_leaf_reg":3,"iterations":150}],"learn":[218.7515254],"iteration":15,"passed_time":28.64846804,"remaining_time":143.2423402,"test":[211.6668957]},
{"parameters":[{"depth":2,"learning_rate":0.03,"l2_leaf_reg":0.2,"iterations":200}],"learn":[218.0142493],"iteration":16,"passed_time":32.28475072,"remaining_time":150.0291357,"test":[211.0518755]},
{"parameters":[{"depth":2,"learning_rate":0.1,"l2_leaf_reg":0.2,"iterations":200}],"learn":[218.7494351],"iteration":17,"passed_time":35.26215022,"remaining_time":152.802651,"test":[211.6644957]},
{"parameters":[{"depth":2,"learning_rate":0.03,"l2_leaf_reg":0.5,"iterations":200}],"learn":[218.0142493],"iteration":18,"passed_time":38.09231779,"remaining_time":154.37413,"test":[211.0518755]},
{"parameters":[{"depth":2,"learning_rate":0.1,"l2_leaf_reg":0.5,"iterations":200}],"learn":[218.7494351],"iteration":19,"passed_time":40.55766913,"remaining_time":154.1191427,"test":[211.6644957]},
{"parameters":[{"depth":2,"learning_rate":0.03,"l2_leaf_reg":1,"iterations":200}],"learn":[218.0142493],"iteration":20,"passed_time":43.07894391,"remaining_time":153.8533711,"test":[211.0518755]},
{"parameters":[{"depth":2,"learning_rate":0.1,"l2_leaf_reg":1,"iterations":200}],"learn":[218.7494351],"iteration":21,"passed_time":45.57409862,"remaining_time":153.2946954,"test":[211.6644957]},
{"parameters":[{"depth":2,"learning_rate":0.03,"l2_leaf_reg":3,"iterations":200}],"learn":[218.0142493],"iteration":22,"passed_time":48.317531,"remaining_time":153.3556419,"test":[211.0518755]},
{"parameters":[{"depth":2,"learning_rate":0.1,"l2_leaf_reg":3,"iterations":200}],"learn":[218.7494351],"iteration":23,"passed_time":51.27755213,"remaining_time":153.8326564,"test":[211.6644957]},
{"parameters":[{"depth":4,"learning_rate":0.03,"l2_leaf_reg":0.2,"iterations":100}],"learn":[218.8655682],"iteration":24,"passed_time":53.71692686,"remaining_time":152.5560723,"test":[213.1221879]},
{"parameters":[{"depth":4,"learning_rate":0.1,"l2_leaf_reg":0.2,"iterations":100}],"learn":[204.7665582],"iteration":25,"passed_time":55.89007396,"remaining_time":150.4732761,"test":[199.6882581]},
{"parameters":[{"depth":4,"learning_rate":0.03,"l2_leaf_reg":0.5,"iterations":100}],"learn":[218.3714461],"iteration":26,"passed_time":58.16287052,"remaining_time":148.6384469,"test":[212.4971196]},
{"parameters":[{"depth":4,"learning_rate":0.1,"l2_leaf_reg":0.5,"iterations":100}],"learn":[204.7665582],"iteration":27,"passed_time":60.61936351,"remaining_time":147.2184542,"test":[199.6882581]},
{"parameters":[{"depth":4,"learning_rate":0.03,"l2_leaf_reg":1,"iterations":100}],"learn":[216.5185605],"iteration":28,"passed_time":63.07024735,"remaining_time":145.7140197,"test":[210.8834034]},
{"parameters":[{"depth":4,"learning_rate":0.1,"l2_leaf_reg":1,"iterations":100}],"learn":[204.8705356],"iteration":29,"passed_time":65.33330538,"remaining_time":143.7332718,"test":[200.0175922]},
{"parameters":[{"depth":4,"learning_rate":0.03,"l2_leaf_reg":3,"iterations":100}],"learn":[216.5185605],"iteration":30,"passed_time":67.58315237,"remaining_time":141.7066098,"test":[210.8834034]},
{"parameters":[{"depth":4,"learning_rate":0.1,"l2_leaf_reg":3,"iterations":100}],"learn":[204.1117967],"iteration":31,"passed_time":70.0194992,"remaining_time":140.0389984,"test":[199.2394234]},
{"parameters":[{"depth":4,"learning_rate":0.03,"l2_leaf_reg":0.2,"iterations":150}],"learn":[213.6031377],"iteration":32,"passed_time":73.56595901,"remaining_time":140.4441036,"test":[208.2884642]},
{"parameters":[{"depth":4,"learning_rate":0.1,"l2_leaf_reg":0.2,"iterations":150}],"learn":[201.7586053],"iteration":33,"passed_time":77.91270319,"remaining_time":142.0761058,"test":[197.7177841]},
{"parameters":[{"depth":4,"learning_rate":0.03,"l2_leaf_reg":0.5,"iterations":150}],"learn":[210.497348],"iteration":34,"passed_time":82.14607339,"remaining_time":143.1688708,"test":[205.3053206]},
{"parameters":[{"depth":4,"learning_rate":0.1,"l2_leaf_reg":0.5,"iterations":150}],"learn":[201.7586053],"iteration":35,"passed_time":86.09078023,"remaining_time":143.4846337,"test":[197.7177841]},
{"parameters":[{"depth":4,"learning_rate":0.03,"l2_leaf_reg":1,"iterations":150}],"learn":[205.6912683],"iteration":36,"passed_time":89.03848574,"remaining_time":141.9802881,"test":[201.2109949]},
{"parameters":[{"depth":4,"learning_rate":0.1,"l2_leaf_reg":1,"iterations":150}],"learn":[200.0239231],"iteration":37,"passed_time":92.51147434,"remaining_time":141.201724,"test":[196.8825745]}
]}